urlup/__init__.py
urlup/__main__.py
urlup/__version__.py
urlup/credentials.py
urlup/errors.py
urlup/http_code.py
urlup/messages.py
urlup/proxy_helper.py
urlup/urlup.py
urlup-1.5.1.data/scripts/urlup
urlup-1.5.1.dist-info/LICENSE
urlup-1.5.1.dist-info/METADATA
urlup-1.5.1.dist-info/WHEEL
urlup-1.5.1.dist-info/top_level.txt
urlup-1.5.1.dist-info/RECORD
